subps.py
subps-1.0.1.dist-info/LICENSE.txt
subps-1.0.1.dist-info/METADATA
subps-1.0.1.dist-info/WHEEL
subps-1.0.1.dist-info/top_level.txt
subps-1.0.1.dist-info/RECORD
