Metadata-Version: 2.1
Name: subps
Version: 1.0.1
Summary: Wrapper script for subprocess usage
Home-page: https://github.com/superstes/python3-subps
Author: René Rath
Author-email: contact@superstes.eu
Project-URL: Repository, https://github.com/superstes/python3-subps
Project-URL: Bug Tracker, https://github.com/superstes/python3-subps/issues
Classifier: Programming Language :: Python :: 3
Classifier: License :: OSI Approved :: GNU General Public License v3 (GPLv3)
Classifier: Operating System :: OS Independent
Requires-Python: >=3.3
License-File: LICENSE.txt
